{"ID V1":1,"ID V10":58,"ID V11":120,"ID V12":677,"ID V13":368,"ID V14":466,"ID V15":17,"ID V16":733,"ID V17":531,"ID V18":360,"ID V19":360,"ID V2":8,"ID V3":2180,"ID V4":97,"ID V5":57,"ID V6":650,"ID V7":4,"ID V8":491,"ID V9":43,"CA ActivoV1 1":1,"CA ActivoV1 2":1,"CA ActivoV1 3":1,"CA ActivoV1 4":1,"CA ActivoV1 5":1,"CA ActivoV1 6":1,"CA ActivoV1 7":1,"CA ActivoV1 8":1,"CA ActivoV1 9":1,"CA ActivoV1 10":1,"CA ActivoV1 11":1,"CA ActivoV1 12":1,"CA ActivoV2 1":1,"CA ActivoV2 2":1,"CA ActivoV2 3":1,"CA ActivoV2 4":1,"CA ActivoV2 5":1,"CA ActivoV2 6":1,"CA ActivoV2 7":1,"CA ActivoV2 8":1,"CA ActivoV2 9":1,"CA ActivoV2 10":1,"CA ActivoV2 11":1,"CA ActivoV2 12":1,"CA NoOk 1":0,"CA NoOk 2":0,"CA NoOk 3":0,"CA NoOk 4":0,"CA NoOk 5":0,"CA NoOk 6":0,"CA NoOk 7":0,"CA NoOk 8":0,"CA NoOk 9":0,"CA NoOk 10":0,"CA NoOk 11":0,"CA NoOk 12":0,"CA Ok 1":1,"CA Ok 2":1,"CA Ok 3":1,"CA Ok 4":1,"CA Ok 5":1,"CA Ok 6":1,"CA Ok 7":1,"CA Ok 8":1,"CA Ok 9":1,"CA Ok 10":1,"CA Ok 11":1,"CA Ok 12":1,"CA Scr 1":0,"CA Scr 2":0,"CA Scr 3":0,"CA Scr 4":0,"CA Scr 5":0,"CA Scr 6":0,"CA Scr 7":0,"CA Scr 8":0,"CA Scr 9":0,"CA Scr 10":0,"CA Scr 11":0,"CA Scr 12":0,"CA V1NoOk 1":0,"CA V1NoOk 2":0,"CA V1NoOk 3":0,"CA V1NoOk 4":0,"CA V1NoOk 5":0,"CA V1NoOk 6":0,"CA V1NoOk 7":0,"CA V1NoOk 8":0,"CA V1NoOk 9":0,"CA V1NoOk 10":0,"CA V1NoOk 11":0,"CA V1NoOk 12":0,"CA V1Ok 1":1,"CA V1Ok 2":1,"CA V1Ok 3":1,"CA V1Ok 4":1,"CA V1Ok 5":1,"CA V1Ok 6":1,"CA V1Ok 7":1,"CA V1Ok 8":1,"CA V1Ok 9":1,"CA V1Ok 10":1,"CA V1Ok 11":1,"CA V1Ok 12":1,"CA V1RealMaximo 1":54,"CA V1RealMaximo 2":201,"CA V1RealMaximo 3":206,"CA V1RealMaximo 4":121,"CA V1RealMaximo 5":202,"CA V1RealMaximo 6":195,"CA V1RealMaximo 7":164,"CA V1RealMaximo 8":162,"CA V1RealMaximo 9":216,"CA V1RealMaximo 10":171,"CA V1RealMaximo 11":167,"CA V1RealMaximo 12":226,"CA V1RealMedio 1":52,"CA V1RealMedio 2":200,"CA V1RealMedio 3":205,"CA V1RealMedio 4":119,"CA V1RealMedio 5":201,"CA V1RealMedio 6":194,"CA V1RealMedio 7":162,"CA V1RealMedio 8":159,"CA V1RealMedio 9":215,"CA V1RealMedio 10":170,"CA V1RealMedio 11":166,"CA V1RealMedio 12":225,"CA V1RealMinimo 1":51,"CA V1RealMinimo 2":200,"CA V1RealMinimo 3":205,"CA V1RealMinimo 4":119,"CA V1RealMinimo 5":201,"CA V1RealMinimo 6":193,"CA V1RealMinimo 7":160,"CA V1RealMinimo 8":156,"CA V1RealMinimo 9":215,"CA V1RealMinimo 10":170,"CA V1RealMinimo 11":165,"CA V1RealMinimo 12":225,"CA V1Scr 1":0,"CA V1Scr 2":0,"CA V1Scr 3":0,"CA V1Scr 4":0,"CA V1Scr 5":0,"CA V1Scr 6":0,"CA V1Scr 7":0,"CA V1Scr 8":0,"CA V1Scr 9":0,"CA V1Scr 10":0,"CA V1Scr 11":0,"CA V1Scr 12":0,"CA V2NoOk 1":0,"CA V2NoOk 2":0,"CA V2NoOk 3":0,"CA V2NoOk 4":0,"CA V2NoOk 5":0,"CA V2NoOk 6":0,"CA V2NoOk 7":0,"CA V2NoOk 8":0,"CA V2NoOk 9":0,"CA V2NoOk 10":0,"CA V2NoOk 11":0,"CA V2NoOk 12":0,"CA V2Ok 1":1,"CA V2Ok 2":1,"CA V2Ok 3":1,"CA V2Ok 4":1,"CA V2Ok 5":1,"CA V2Ok 6":1,"CA V2Ok 7":1,"CA V2Ok 8":1,"CA V2Ok 9":1,"CA V2Ok 10":1,"CA V2Ok 11":1,"CA V2Ok 12":1,"CA V2RealMaximo 1":967,"CA V2RealMaximo 2":993,"CA V2RealMaximo 3":1041,"CA V2RealMaximo 4":1031,"CA V2RealMaximo 5":511,"CA V2RealMaximo 6":808,"CA V2RealMaximo 7":654,"CA V2RealMaximo 8":881,"CA V2RealMaximo 9":626,"CA V2RealMaximo 10":984,"CA V2RealMaximo 11":832,"CA V2RealMaximo 12":612,"CA V2RealMedio 1":965,"CA V2RealMedio 2":991,"CA V2RealMedio 3":1040,"CA V2RealMedio 4":1026,"CA V2RealMedio 5":509,"CA V2RealMedio 6":799,"CA V2RealMedio 7":653,"CA V2RealMedio 8":871,"CA V2RealMedio 9":626,"CA V2RealMedio 10":982,"CA V2RealMedio 11":816,"CA V2RealMedio 12":609,"CA V2RealMinimo 1":964,"CA V2RealMinimo 2":990,"CA V2RealMinimo 3":1040,"CA V2RealMinimo 4":1022,"CA V2RealMinimo 5":508,"CA V2RealMinimo 6":790,"CA V2RealMinimo 7":653,"CA V2RealMinimo 8":863,"CA V2RealMinimo 9":626,"CA V2RealMinimo 10":980,"CA V2RealMinimo 11":807,"CA V2RealMinimo 12":608,"CA V2Scr 1":0,"CA V2Scr 2":0,"CA V2Scr 3":0,"CA V2Scr 4":0,"CA V2Scr 5":0,"CA V2Scr 6":0,"CA V2Scr 7":0,"CA V2Scr 8":0,"CA V2Scr 9":0,"CA V2Scr 10":0,"CA V2Scr 11":0,"CA V2Scr 12":0,"CM Activo 1":1,"CM NoOk 1":0,"CM Ok 1":1,"CM RealMaximo 1":87,"CM RealMedio 1":87,"CM RealMinimo 1":87,"CM Scr 1":0,"CJ ActivoV1 1":1,"CJ ActivoV1 4":1,"CJ ActivoV1 7":1,"CJ ActivoV1 10":1,"CJ ActivoV1 11":1,"CJ ActivoV1 12":1,"CJ ActivoV1 13":1,"CJ ActivoV1 16":1,"CJ ActivoV1 17":1,"CJ ActivoV1 18":1,"CJ ActivoV1 19":1,"CJ ActivoV1 20":0,"CJ ActivoV1 22":1,"CJ ActivoV1 23":1,"CJ ActivoV1 25":1,"CJ ActivoV1 28":1,"CJ ActivoV1 31":1,"CJ ActivoV1 32":0,"CJ ActivoV1 34":1,"CJ ActivoV1 49":1,"CJ ActivoV1 50":1,"CJ ActivoV1 51":1,"CJ ActivoV1 52":1,"CJ ActivoV2 1":1,"CJ ActivoV2 4":1,"CJ ActivoV2 7":1,"CJ ActivoV2 10":1,"CJ ActivoV2 11":1,"CJ ActivoV2 12":1,"CJ ActivoV2 13":1,"CJ ActivoV2 16":1,"CJ ActivoV2 17":1,"CJ ActivoV2 18":1,"CJ ActivoV2 19":1,"CJ ActivoV2 20":0,"CJ ActivoV2 22":1,"CJ ActivoV2 23":1,"CJ ActivoV2 25":1,"CJ ActivoV2 28":1,"CJ ActivoV2 31":1,"CJ ActivoV2 32":0,"CJ ActivoV2 34":1,"CJ ActivoV2 49":1,"CJ ActivoV2 50":1,"CJ ActivoV2 51":1,"CJ ActivoV2 52":1,"CJ NoOk 1":0,"CJ NoOk 4":0,"CJ NoOk 7":0,"CJ NoOk 10":0,"CJ NoOk 11":0,"CJ NoOk 12":0,"CJ NoOk 13":0,"CJ NoOk 16":0,"CJ NoOk 17":0,"CJ NoOk 18":0,"CJ NoOk 19":0,"CJ NoOk 20":0,"CJ NoOk 22":0,"CJ NoOk 23":0,"CJ NoOk 25":0,"CJ NoOk 28":0,"CJ NoOk 31":0,"CJ NoOk 32":0,"CJ NoOk 34":0,"CJ NoOk 49":0,"CJ NoOk 50":0,"CJ NoOk 51":0,"CJ NoOk 52":0,"CJ Ok 1":1,"CJ Ok 4":1,"CJ Ok 7":1,"CJ Ok 10":1,"CJ Ok 11":1,"CJ Ok 12":1,"CJ Ok 13":1,"CJ Ok 16":1,"CJ Ok 17":1,"CJ Ok 18":1,"CJ Ok 19":1,"CJ Ok 20":0,"CJ Ok 22":1,"CJ Ok 23":1,"CJ Ok 25":1,"CJ Ok 28":1,"CJ Ok 31":1,"CJ Ok 32":0,"CJ Ok 34":1,"CJ Ok 49":1,"CJ Ok 50":1,"CJ Ok 51":1,"CJ Ok 52":1,"CJ Scr 1":0,"CJ Scr 4":0,"CJ Scr 7":0,"CJ Scr 10":0,"CJ Scr 11":0,"CJ Scr 12":0,"CJ Scr 13":0,"CJ Scr 16":0,"CJ Scr 17":0,"CJ Scr 18":0,"CJ Scr 19":0,"CJ Scr 20":0,"CJ Scr 22":0,"CJ Scr 23":0,"CJ Scr 25":0,"CJ Scr 28":0,"CJ Scr 31":0,"CJ Scr 32":0,"CJ Scr 34":0,"CJ Scr 49":0,"CJ Scr 50":0,"CJ Scr 51":0,"CJ Scr 52":0,"CJ V1NoOk 1":0,"CJ V1NoOk 4":0,"CJ V1NoOk 7":0,"CJ V1NoOk 10":0,"CJ V1NoOk 11":0,"CJ V1NoOk 12":0,"CJ V1NoOk 13":0,"CJ V1NoOk 16":0,"CJ V1NoOk 17":0,"CJ V1NoOk 18":0,"CJ V1NoOk 19":0,"CJ V1NoOk 20":0,"CJ V1NoOk 22":0,"CJ V1NoOk 23":0,"CJ V1NoOk 25":0,"CJ V1NoOk 28":0,"CJ V1NoOk 31":0,"CJ V1NoOk 32":0,"CJ V1NoOk 34":0,"CJ V1NoOk 49":0,"CJ V1NoOk 50":0,"CJ V1NoOk 51":0,"CJ V1NoOk 52":0,"CJ V1Ok 1":1,"CJ V1Ok 4":1,"CJ V1Ok 7":1,"CJ V1Ok 10":1,"CJ V1Ok 11":1,"CJ V1Ok 12":1,"CJ V1Ok 13":1,"CJ V1Ok 16":1,"CJ V1Ok 17":1,"CJ V1Ok 18":1,"CJ V1Ok 19":1,"CJ V1Ok 20":0,"CJ V1Ok 22":1,"CJ V1Ok 23":1,"CJ V1Ok 25":1,"CJ V1Ok 28":1,"CJ V1Ok 31":1,"CJ V1Ok 32":0,"CJ V1Ok 34":1,"CJ V1Ok 49":1,"CJ V1Ok 50":1,"CJ V1Ok 51":1,"CJ V1Ok 52":1,"CJ V1RealMaximo 1":82,"CJ V1RealMaximo 4":83,"CJ V1RealMaximo 7":65,"CJ V1RealMaximo 10":24,"CJ V1RealMaximo 11":11,"CJ V1RealMaximo 12":10,"CJ V1RealMaximo 13":62,"CJ V1RealMaximo 16":14,"CJ V1RealMaximo 17":17,"CJ V1RealMaximo 18":14,"CJ V1RealMaximo 19":76,"CJ V1RealMaximo 20":0,"CJ V1RealMaximo 22":68,"CJ V1RealMaximo 23":24,"CJ V1RealMaximo 25":73,"CJ V1RealMaximo 28":76,"CJ V1RealMaximo 31":36,"CJ V1RealMaximo 32":0,"CJ V1RealMaximo 34":94,"CJ V1RealMaximo 49":13,"CJ V1RealMaximo 50":16,"CJ V1RealMaximo 51":14,"CJ V1RealMaximo 52":16,"CJ V1RealMedio 1":82,"CJ V1RealMedio 4":83,"CJ V1RealMedio 7":65,"CJ V1RealMedio 10":23,"CJ V1RealMedio 11":11,"CJ V1RealMedio 12":10,"CJ V1RealMedio 13":61,"CJ V1RealMedio 16":14,"CJ V1RealMedio 17":17,"CJ V1RealMedio 18":14,"CJ V1RealMedio 19":76,"CJ V1RealMedio 20":0,"CJ V1RealMedio 22":68,"CJ V1RealMedio 23":24,"CJ V1RealMedio 25":72,"CJ V1RealMedio 28":76,"CJ V1RealMedio 31":36,"CJ V1RealMedio 32":0,"CJ V1RealMedio 34":94,"CJ V1RealMedio 49":12,"CJ V1RealMedio 50":16,"CJ V1RealMedio 51":14,"CJ V1RealMedio 52":16,"CJ V1RealMinimo 1":82,"CJ V1RealMinimo 4":83,"CJ V1RealMinimo 7":65,"CJ V1RealMinimo 10":23,"CJ V1RealMinimo 11":11,"CJ V1RealMinimo 12":10,"CJ V1RealMinimo 13":61,"CJ V1RealMinimo 16":14,"CJ V1RealMinimo 17":17,"CJ V1RealMinimo 18":14,"CJ V1RealMinimo 19":76,"CJ V1RealMinimo 20":0,"CJ V1RealMinimo 22":68,"CJ V1RealMinimo 23":24,"CJ V1RealMinimo 25":72,"CJ V1RealMinimo 28":76,"CJ V1RealMinimo 31":36,"CJ V1RealMinimo 32":0,"CJ V1RealMinimo 34":94,"CJ V1RealMinimo 49":12,"CJ V1RealMinimo 50":16,"CJ V1RealMinimo 51":14,"CJ V1RealMinimo 52":16,"CJ V1Scr 1":0,"CJ V1Scr 4":0,"CJ V1Scr 7":0,"CJ V1Scr 10":0,"CJ V1Scr 11":0,"CJ V1Scr 12":0,"CJ V1Scr 13":0,"CJ V1Scr 16":0,"CJ V1Scr 17":0,"CJ V1Scr 18":0,"CJ V1Scr 19":0,"CJ V1Scr 20":0,"CJ V1Scr 22":0,"CJ V1Scr 23":0,"CJ V1Scr 25":0,"CJ V1Scr 28":0,"CJ V1Scr 31":0,"CJ V1Scr 32":0,"CJ V1Scr 34":0,"CJ V1Scr 49":0,"CJ V1Scr 50":0,"CJ V1Scr 51":0,"CJ V1Scr 52":0,"CJ V2NoOk 1":0,"CJ V2NoOk 4":0,"CJ V2NoOk 7":0,"CJ V2NoOk 10":0,"CJ V2NoOk 11":0,"CJ V2NoOk 12":0,"CJ V2NoOk 13":0,"CJ V2NoOk 16":0,"CJ V2NoOk 17":0,"CJ V2NoOk 18":0,"CJ V2NoOk 19":0,"CJ V2NoOk 20":0,"CJ V2NoOk 22":0,"CJ V2NoOk 23":0,"CJ V2NoOk 25":0,"CJ V2NoOk 28":0,"CJ V2NoOk 31":0,"CJ V2NoOk 32":0,"CJ V2NoOk 34":0,"CJ V2NoOk 49":0,"CJ V2NoOk 50":0,"CJ V2NoOk 51":0,"CJ V2NoOk 52":0,"CJ V2Ok 1":1,"CJ V2Ok 4":1,"CJ V2Ok 7":1,"CJ V2Ok 10":1,"CJ V2Ok 11":1,"CJ V2Ok 12":1,"CJ V2Ok 13":1,"CJ V2Ok 16":1,"CJ V2Ok 17":1,"CJ V2Ok 18":1,"CJ V2Ok 19":1,"CJ V2Ok 20":0,"CJ V2Ok 22":1,"CJ V2Ok 23":1,"CJ V2Ok 25":1,"CJ V2Ok 28":1,"CJ V2Ok 31":1,"CJ V2Ok 32":0,"CJ V2Ok 34":1,"CJ V2Ok 49":1,"CJ V2Ok 50":1,"CJ V2Ok 51":1,"CJ V2Ok 52":1,"CJ V2RealMaximo 1":531,"CJ V2RealMaximo 4":545,"CJ V2RealMaximo 7":464,"CJ V2RealMaximo 10":645,"CJ V2RealMaximo 11":677,"CJ V2RealMaximo 12":673,"CJ V2RealMaximo 13":523,"CJ V2RealMaximo 16":727,"CJ V2RealMaximo 17":723,"CJ V2RealMaximo 18":722,"CJ V2RealMaximo 19":603,"CJ V2RealMaximo 20":0,"CJ V2RealMaximo 22":626,"CJ V2RealMaximo 23":541,"CJ V2RealMaximo 25":477,"CJ V2RealMaximo 28":443,"CJ V2RealMaximo 31":419,"CJ V2RealMaximo 32":0,"CJ V2RealMaximo 34":343,"CJ V2RealMaximo 49":742,"CJ V2RealMaximo 50":655,"CJ V2RealMaximo 51":751,"CJ V2RealMaximo 52":715,"CJ V2RealMedio 1":531,"CJ V2RealMedio 4":544,"CJ V2RealMedio 7":464,"CJ V2RealMedio 10":644,"CJ V2RealMedio 11":676,"CJ V2RealMedio 12":670,"CJ V2RealMedio 13":521,"CJ V2RealMedio 16":724,"CJ V2RealMedio 17":723,"CJ V2RealMedio 18":721,"CJ V2RealMedio 19":601,"CJ V2RealMedio 20":0,"CJ V2RealMedio 22":625,"CJ V2RealMedio 23":540,"CJ V2RealMedio 25":475,"CJ V2RealMedio 28":443,"CJ V2RealMedio 31":416,"CJ V2RealMedio 32":0,"CJ V2RealMedio 34":343,"CJ V2RealMedio 49":741,"CJ V2RealMedio 50":654,"CJ V2RealMedio 51":749,"CJ V2RealMedio 52":714,"CJ V2RealMinimo 1":531,"CJ V2RealMinimo 4":544,"CJ V2RealMinimo 7":464,"CJ V2RealMinimo 10":644,"CJ V2RealMinimo 11":674,"CJ V2RealMinimo 12":668,"CJ V2RealMinimo 13":519,"CJ V2RealMinimo 16":722,"CJ V2RealMinimo 17":723,"CJ V2RealMinimo 18":721,"CJ V2RealMinimo 19":601,"CJ V2RealMinimo 20":0,"CJ V2RealMinimo 22":625,"CJ V2RealMinimo 23":540,"CJ V2RealMinimo 25":475,"CJ V2RealMinimo 28":443,"CJ V2RealMinimo 31":414,"CJ V2RealMinimo 32":0,"CJ V2RealMinimo 34":343,"CJ V2RealMinimo 49":741,"CJ V2RealMinimo 50":654,"CJ V2RealMinimo 51":748,"CJ V2RealMinimo 52":714,"CJ V2Scr 1":0,"CJ V2Scr 4":0,"CJ V2Scr 7":0,"CJ V2Scr 10":0,"CJ V2Scr 11":0,"CJ V2Scr 12":0,"CJ V2Scr 13":0,"CJ V2Scr 16":0,"CJ V2Scr 17":0,"CJ V2Scr 18":0,"CJ V2Scr 19":0,"CJ V2Scr 20":0,"CJ V2Scr 22":0,"CJ V2Scr 23":0,"CJ V2Scr 25":0,"CJ V2Scr 28":0,"CJ V2Scr 31":0,"CJ V2Scr 32":0,"CJ V2Scr 34":0,"CJ V2Scr 49":0,"CJ V2Scr 50":0,"CJ V2Scr 51":0,"CJ V2Scr 52":0,"CP Activo":1,"CP Ok":1,"CP NoOk":0,"CP Scr":0,"CP RealMinimo":337,"CP RealMedio":360,"CP RealMaximo":404,"CPG Activo 1":1,"CPG Activo 2":1,"CPG NoOk 1":0,"CPG NoOk 2":0,"CPG Ok 1":0,"CPG Ok 2":0,"CPG RealMaximo 1":748,"CPG RealMaximo 2":1022,"CPG RealMedio 1":657,"CPG RealMedio 2":851,"CPG RealMinimo 1":630,"CPG RealMinimo 2":780,"CPG Scr 1":0,"CPG Scr 2":0,"CS Activo 1":1,"CS Activo 2":1,"CS Activo 3":1,"CS Activo 4":1,"CS Activo 5":1,"CS Activo 6":1,"CS Activo 7":1,"CS Activo 8":1,"CS Activo 9":1,"CS Activo 10":1,"CS Activo 11":1,"CS Activo 12":1,"CS Activo 13":1,"CS Activo 14":1,"CS Activo 16":1,"CS Activo 18":1,"CS Activo 25":1,"CS Activo 26":1,"CS Activo 27":1,"CS Activo 28":1,"CS Activo 29":1,"CS Activo 30":1,"CS Activo 31":1,"CS Activo 32":1,"CS Activo 33":1,"CS Activo 34":1,"CS Activo 35":1,"CS Activo 36":1,"CS Activo 37":0,"CS Activo 38":0,"CS Activo 39":1,"CS Activo 40":1,"CS Activo 41":1,"CS Activo 42":1,"CS Activo 43":1,"CS Activo 44":1,"CS Activo 45":1,"CS Activo 46":1,"CS Activo 47":1,"CS Activo 48":1,"CS Activo 49":1,"CS Activo 50":1,"CS Activo 51":1,"CS Activo 52":1,"CS Activo 53":1,"CS Activo 54":1,"CS NoOk 1":0,"CS NoOk 2":0,"CS NoOk 3":0,"CS NoOk 4":0,"CS NoOk 5":0,"CS NoOk 6":0,"CS NoOk 7":0,"CS NoOk 8":0,"CS NoOk 9":0,"CS NoOk 10":0,"CS NoOk 11":0,"CS NoOk 12":0,"CS NoOk 13":0,"CS NoOk 14":0,"CS NoOk 16":0,"CS NoOk 18":0,"CS NoOk 25":0,"CS NoOk 26":0,"CS NoOk 27":0,"CS NoOk 28":0,"CS NoOk 29":0,"CS NoOk 30":0,"CS NoOk 31":0,"CS NoOk 32":0,"CS NoOk 33":0,"CS NoOk 34":0,"CS NoOk 35":0,"CS NoOk 36":0,"CS NoOk 37":0,"CS NoOk 38":0,"CS NoOk 39":0,"CS NoOk 40":0,"CS NoOk 41":0,"CS NoOk 42":0,"CS NoOk 43":0,"CS NoOk 44":0,"CS NoOk 45":0,"CS NoOk 46":0,"CS NoOk 47":0,"CS NoOk 48":0,"CS NoOk 49":0,"CS NoOk 50":0,"CS NoOk 51":0,"CS NoOk 52":0,"CS NoOk 53":0,"CS NoOk 54":0,"CS Ok 1":1,"CS Ok 2":1,"CS Ok 3":1,"CS Ok 4":1,"CS Ok 5":1,"CS Ok 6":1,"CS Ok 7":1,"CS Ok 8":1,"CS Ok 9":1,"CS Ok 10":1,"CS Ok 11":1,"CS Ok 12":1,"CS Ok 13":1,"CS Ok 14":1,"CS Ok 16":1,"CS Ok 18":1,"CS Ok 25":1,"CS Ok 26":1,"CS Ok 27":1,"CS Ok 28":1,"CS Ok 29":1,"CS Ok 30":1,"CS Ok 31":1,"CS Ok 32":1,"CS Ok 33":1,"CS Ok 34":1,"CS Ok 35":1,"CS Ok 36":1,"CS Ok 37":0,"CS Ok 38":0,"CS Ok 39":1,"CS Ok 40":1,"CS Ok 41":1,"CS Ok 42":1,"CS Ok 43":1,"CS Ok 44":1,"CS Ok 45":1,"CS Ok 46":1,"CS Ok 47":1,"CS Ok 48":1,"CS Ok 49":1,"CS Ok 50":1,"CS Ok 51":1,"CS Ok 52":1,"CS Ok 53":1,"CS Ok 54":1,"CS RealMaximo 1":208,"CS RealMaximo 2":207,"CS RealMaximo 3":212,"CS RealMaximo 4":178,"CS RealMaximo 5":208,"CS RealMaximo 6":122,"CS RealMaximo 7":52,"CS RealMaximo 8":44,"CS RealMaximo 9":200,"CS RealMaximo 10":36,"CS RealMaximo 11":250,"CS RealMaximo 12":171,"CS RealMaximo 13":204,"CS RealMaximo 14":193,"CS RealMaximo 16":211,"CS RealMaximo 18":198,"CS RealMaximo 25":60,"CS RealMaximo 26":58,"CS RealMaximo 27":54,"CS RealMaximo 28":68,"CS RealMaximo 29":39,"CS RealMaximo 30":143,"CS RealMaximo 31":47,"CS RealMaximo 32":150,"CS RealMaximo 33":38,"CS RealMaximo 34":36,"CS RealMaximo 35":88,"CS RealMaximo 36":73,"CS RealMaximo 37":0,"CS RealMaximo 38":0,"CS RealMaximo 39":161,"CS RealMaximo 40":118,"CS RealMaximo 41":179,"CS RealMaximo 42":157,"CS RealMaximo 43":143,"CS RealMaximo 44":152,"CS RealMaximo 45":124,"CS RealMaximo 46":55,"CS RealMaximo 47":30,"CS RealMaximo 48":68,"CS RealMaximo 49":50,"CS RealMaximo 50":90,"CS RealMaximo 51":164,"CS RealMaximo 52":154,"CS RealMaximo 53":160,"CS RealMaximo 54":159,"CS RealMedio 1":184,"CS RealMedio 2":182,"CS RealMedio 3":188,"CS RealMedio 4":157,"CS RealMedio 5":186,"CS RealMedio 6":117,"CS RealMedio 7":47,"CS RealMedio 8":40,"CS RealMedio 9":193,"CS RealMedio 10":30,"CS RealMedio 11":232,"CS RealMedio 12":153,"CS RealMedio 13":189,"CS RealMedio 14":172,"CS RealMedio 16":186,"CS RealMedio 18":175,"CS RealMedio 25":53,"CS RealMedio 26":52,"CS RealMedio 27":49,"CS RealMedio 28":61,"CS RealMedio 29":35,"CS RealMedio 30":129,"CS RealMedio 31":41,"CS RealMedio 32":145,"CS RealMedio 33":36,"CS RealMedio 34":32,"CS RealMedio 35":79,"CS RealMedio 36":66,"CS RealMedio 37":0,"CS RealMedio 38":0,"CS RealMedio 39":154,"CS RealMedio 40":113,"CS RealMedio 41":170,"CS RealMedio 42":150,"CS RealMedio 43":138,"CS RealMedio 44":145,"CS RealMedio 45":117,"CS RealMedio 46":52,"CS RealMedio 47":29,"CS RealMedio 48":64,"CS RealMedio 49":48,"CS RealMedio 50":88,"CS RealMedio 51":156,"CS RealMedio 52":146,"CS RealMedio 53":152,"CS RealMedio 54":151,"CS RealMinimo 1":159,"CS RealMinimo 2":172,"CS RealMinimo 3":176,"CS RealMinimo 4":137,"CS RealMinimo 5":163,"CS RealMinimo 6":114,"CS RealMinimo 7":41,"CS RealMinimo 8":35,"CS RealMinimo 9":189,"CS RealMinimo 10":24,"CS RealMinimo 11":220,"CS RealMinimo 12":134,"CS RealMinimo 13":169,"CS RealMinimo 14":165,"CS RealMinimo 16":164,"CS RealMinimo 18":155,"CS RealMinimo 25":48,"CS RealMinimo 26":47,"CS RealMinimo 27":44,"CS RealMinimo 28":55,"CS RealMinimo 29":31,"CS RealMinimo 30":114,"CS RealMinimo 31":36,"CS RealMinimo 32":143,"CS RealMinimo 33":33,"CS RealMinimo 34":29,"CS RealMinimo 35":71,"CS RealMinimo 36":59,"CS RealMinimo 37":0,"CS RealMinimo 38":0,"CS RealMinimo 39":140,"CS RealMinimo 40":97,"CS RealMinimo 41":156,"CS RealMinimo 42":137,"CS RealMinimo 43":125,"CS RealMinimo 44":124,"CS RealMinimo 45":107,"CS RealMinimo 46":48,"CS RealMinimo 47":28,"CS RealMinimo 48":59,"CS RealMinimo 49":43,"CS RealMinimo 50":84,"CS RealMinimo 51":142,"CS RealMinimo 52":134,"CS RealMinimo 53":138,"CS RealMinimo 54":138,"CS Scr 1":0,"CS Scr 2":0,"CS Scr 3":0,"CS Scr 4":0,"CS Scr 5":0,"CS Scr 6":0,"CS Scr 7":0,"CS Scr 8":0,"CS Scr 9":0,"CS Scr 10":0,"CS Scr 11":0,"CS Scr 12":0,"CS Scr 13":0,"CS Scr 14":0,"CS Scr 16":0,"CS Scr 18":0,"CS Scr 25":0,"CS Scr 26":0,"CS Scr 27":0,"CS Scr 28":0,"CS Scr 29":0,"CS Scr 30":0,"CS Scr 31":0,"CS Scr 32":0,"CS Scr 33":0,"CS Scr 34":0,"CS Scr 35":0,"CS Scr 36":0,"CS Scr 37":0,"CS Scr 38":0,"CS Scr 39":0,"CS Scr 40":0,"CS Scr 41":0,"CS Scr 42":0,"CS Scr 43":0,"CS Scr 44":0,"CS Scr 45":0,"CS Scr 46":0,"CS Scr 47":0,"CS Scr 48":0,"CS Scr 49":0,"CS Scr 50":0,"CS Scr 51":0,"CS Scr 52":0,"CS Scr 53":0,"CS Scr 54":0,"CV V1":0,"CV V2":0,"CV V3":0,"CV V4":247.636,"CV V5":291.703,"CV V6":551.667,"CV V7":0,"CV V8":273.166,"CV V9":546.694,"CV V10":0,"CV V11":364.945,"CV V12":823.712,"CV V13":0,"IMP Paso":0}